gperc/__init__.py
gperc/__main__.py
gperc/arrow.py
gperc/cli.py
gperc/configs.py
gperc/data.py
gperc/fastlibs/README.md
gperc/fastlibs/cargo.toml
gperc/fastlibs/src/lib.rs
gperc/fastlibs/tests.py
gperc/models.py
gperc/trainer.py
gperc/utils.py
gperc-0.7.dist-info/LICENSE
gperc-0.7.dist-info/WHEEL
gperc-0.7.dist-info/METADATA
gperc-0.7.dist-info/RECORD
