Metadata-Version: 2.1
Name: gperc
Version: 0.7
Summary: General purpose perceiver architectures!
License: MIT
Author: yashbonde
Author-email: bonde.yash97@gmail.com
Requires-Python: >=3.6,<4.0
Classifier: License :: OSI Approved :: MIT License
Classifier: Programming Language :: Python :: 3
Classifier: Programming Language :: Python :: 3.6
Classifier: Programming Language :: Python :: 3.7
Classifier: Programming Language :: Python :: 3.8
Classifier: Programming Language :: Python :: 3.9
Requires-Dist: datasets (==1.12.1)
Requires-Dist: fire (>=0.4.0,<0.5.0)
Requires-Dist: numpy (>=1.19.0,<2.0.0)
Requires-Dist: torch (>=1.9.0,<2.0.0)
Requires-Dist: tqdm (>=4.62.2,<5.0.0)
